eh_fifty.py
eh_fifty-0.3.0.dist-info/METADATA
eh_fifty-0.3.0.dist-info/WHEEL
eh_fifty-0.3.0.dist-info/licenses/LICENSE.txt
eh_fifty-0.3.0.dist-info/RECORD
