Metadata-Version: 2.4
Name: eh-fifty
Version: 0.3.0
Summary: Library for configuring the Astro A50 wireless headset and base station (generation 4)
Project-URL: Homepage, https://github.com/tdryer/eh-fifty
Author-email: Tom Dryer <tomdryer.com@gmail.com>
License-File: LICENSE.txt
Classifier: License :: OSI Approved :: MIT License
Classifier: Operating System :: OS Independent
Classifier: Programming Language :: Python :: 3
Requires-Python: >=3.7
Requires-Dist: pyusb<2,>=1.2.1
Requires-Dist: simple-hexdump==0.0.1
